airbagclimenu/Menu.py
airbagclimenu/__init__.py
airbagclimenu-1.2.4.dist-info/METADATA
airbagclimenu-1.2.4.dist-info/WHEEL
airbagclimenu-1.2.4.dist-info/licenses/LICENSE
airbagclimenu-1.2.4.dist-info/RECORD
