Metadata-Version: 2.3
Name: airbagclimenu
Version: 1.2.4
Summary: A python package that makes it easy and intuitive to create good looking CLI menus
Project-URL: Homepage, https://github.com/Airbag65/CLI-Menu
Project-URL: Issues, https://github.com/Airbag65/CLI-Menu/issues
Author-email: Anton Norman <normananton03@gmail.com>
License-File: LICENSE
Classifier: License :: OSI Approved :: MIT License
Classifier: Operating System :: OS Independent
Classifier: Programming Language :: Python :: 3
Requires-Python: >=3.8
